{
  "workflow_version": "1.2.0",
  "timestamps": {
    "started": "2025-12-03T09:35:00+05:30",
    "last_updated": "2025-12-03T09:40:00+05:30"
  },
  "mode": "initial_scan",
  "scan_level": "exhaustive",
  "project_root": "/Users/hp/Desktop/Work/Repositories/Astr",
  "output_folder": "/Users/hp/Desktop/Work/Repositories/Astr/docs",
  "completed_steps": [
    {
      "step": "step_1",
      "status": "completed",
      "timestamp": "2025-12-03T09:38:00+05:30",
      "summary": "Classified as Multi-part (Mobile + Backend)"
    },
    {
      "step": "step_3",
      "status": "completed",
      "timestamp": "2025-12-03T09:38:00+05:30",
      "summary": "Tech stack: Flutter (Mobile), Flask (Backend)"
    },
    {
      "step": "step_2",
      "status": "completed",
      "timestamp": "2025-12-03T09:40:00+05:30",
      "summary": "Found 2 active docs (README, CONTRIBUTING) and archived docs"
    }
  ],
  "current_step": "step_4",
  "findings": {
    "project_classification": {
      "type": "multi-part",
      "parts": [
        {
          "id": "mobile",
          "name": "Mobile App",
          "root": "/",
          "type": "mobile",
          "tech": "Flutter"
        },
        {
          "id": "backend",
          "name": "Backend API",
          "root": "backend/",
          "type": "backend",
          "tech": "Flask"
        }
      ]
    },
    "technology_stack": {
      "mobile": {
        "framework": "Flutter",
        "language": "Dart",
        "state_management": "Riverpod",
        "routing": "GoRouter",
        "local_storage": "Hive",
        "astronomy": "Swiss Ephemeris (sweph)"
      },
      "backend": {
        "framework": "Flask",
        "language": "Python",
        "database": "MongoDB (PyMongo)",
        "runtime": "Vercel Serverless"
      }
    },
    "existing_docs": [
      {
        "path": "README.md",
        "type": "readme"
      },
      {
        "path": "CONTRIBUTING.md",
        "type": "contributing"
      }
    ]
  },
  "outputs_generated": [
    "project-scan-report.json"
  ],
  "resume_instructions": "Continue from step 4 (Conditional Analysis)"
}